ssoclient/__init__.py
ssoclient/tests/__init__.py
ssoclient/tests/test_v2.py
ssoclient/v2/__init__.py
ssoclient/v2/client.py
ssoclient/v2/errors.py
ssoclient/v2/http.py
ssoclient-2.1.1.dist-info/DESCRIPTION.rst
ssoclient-2.1.1.dist-info/METADATA
ssoclient-2.1.1.dist-info/RECORD
ssoclient-2.1.1.dist-info/WHEEL
ssoclient-2.1.1.dist-info/metadata.json
ssoclient-2.1.1.dist-info/top_level.txt
