Metadata-Version: 2.0
Name: ssoclient
Version: 2.1.1
Summary: UNKNOWN
Home-page: UNKNOWN
Author: Canonical ISD Hackers
Author-email: canonical-isd@lists.launchpad.net
License: AGPLv3
Platform: UNKNOWN
Requires-Dist: requests
Requires-Dist: requests-oauthlib
